{
  "products": [
    {
      "name": "Iphone 12 Promax Pro",
      "price": 100,
      "status": "true",
      "id": 1
    },
    {
      "name": "Samsung Glaxy S21 mới nhất",
      "price": 200,
      "status": "true",
      "id": 2
    },
    {
      "name": "Realme 7",
      "price": 500,
      "status": "false",
      "id": 3
    },
    {
      "name": "Xiaomi",
      "price": 12000,
      "status": "false",
      "id": 5
    },
    {
      "name": "Oppo",
      "price": 6969,
      "status": "false",
      "id": 6
    }
  ]
}